{
    "os": "Linux-6.5.0-35-generic-x86_64-with-glibc2.35",
    "python": "3.9.18",
    "heartbeatAt": "2024-05-23T08:09:47.117534",
    "startedAt": "2024-05-23T08:09:46.475419",
    "docker": null,
    "cuda": null,
    "args": [
        "--seed",
        "293",
        "--env_name",
        "StarCraft2",
        "--experiment_name",
        "sigmoid_flipsigmoid_weighted_l1loss_shaping_MAPPO",
        "--group_name",
        "sigmoid_flipsigmoid_weighted_l1loss_shaping_MAPPO",
        "--shaping_weight_type",
        "sigmoid_flipsigmoid",
        "--num_gpu",
        "1"
    ],
    "state": "running",
    "program": "/home/uosai/Desktop/on-policy/onpolicy/scripts/train/train_smac.py",
    "codePathLocal": "train_smac.py",
    "codePath": "onpolicy/scripts/train/train_smac.py",
    "git": {
        "remote": "https://github.com/narame7/on-policy.git",
        "commit": "a843a882a6e81ddd9b6e30e03a1d91e4076549c9"
    },
    "email": "singfor7012@gmail.com",
    "root": "/home/uosai/Desktop/on-policy",
    "host": "uos-desktop",
    "username": "uosai",
    "executable": "/home/uosai/Desktop/miniconda3/envs/marl/bin/python",
    "cpu_count": 12,
    "cpu_count_logical": 24,
    "cpu_freq": {
        "current": 4359.642625,
        "min": 2200.0,
        "max": 3700.0
    },
    "cpu_freq_per_core": [
        {
            "current": 4377.745,
            "min": 2200.0,
            "max": 3700.0
        },
        {
            "current": 4378.502,
            "min": 2200.0,
            "max": 3700.0
        },
        {
            "current": 4378.449,
            "min": 2200.0,
            "max": 3700.0
        },
        {
            "current": 4378.392,
            "min": 2200.0,
            "max": 3700.0
        },
        {
            "current": 4378.517,
            "min": 2200.0,
            "max": 3700.0
        },
        {
            "current": 4379.208,
            "min": 2200.0,
            "max": 3700.0
        },
        {
            "current": 4387.963,
            "min": 2200.0,
            "max": 3700.0
        },
        {
            "current": 4378.516,
            "min": 2200.0,
            "max": 3700.0
        },
        {
            "current": 4378.533,
            "min": 2200.0,
            "max": 3700.0
        },
        {
            "current": 4378.513,
            "min": 2200.0,
            "max": 3700.0
        },
        {
            "current": 4391.497,
            "min": 2200.0,
            "max": 3700.0
        },
        {
            "current": 4378.521,
            "min": 2200.0,
            "max": 3700.0
        },
        {
            "current": 4378.517,
            "min": 2200.0,
            "max": 3700.0
        },
        {
            "current": 4378.496,
            "min": 2200.0,
            "max": 3700.0
        },
        {
            "current": 4378.532,
            "min": 2200.0,
            "max": 3700.0
        },
        {
            "current": 4382.393,
            "min": 2200.0,
            "max": 3700.0
        },
        {
            "current": 4377.157,
            "min": 2200.0,
            "max": 3700.0
        },
        {
            "current": 4378.681,
            "min": 2200.0,
            "max": 3700.0
        },
        {
            "current": 4378.53,
            "min": 2200.0,
            "max": 3700.0
        },
        {
            "current": 4378.532,
            "min": 2200.0,
            "max": 3700.0
        },
        {
            "current": 4378.506,
            "min": 2200.0,
            "max": 3700.0
        },
        {
            "current": 4377.796,
            "min": 2200.0,
            "max": 3700.0
        },
        {
            "current": 4377.719,
            "min": 2200.0,
            "max": 3700.0
        },
        {
            "current": 4378.517,
            "min": 2200.0,
            "max": 3700.0
        }
    ],
    "disk": {
        "/": {
            "total": 233.17998886108398,
            "used": 180.04729843139648
        }
    },
    "gpu": "NVIDIA GeForce RTX 3080",
    "gpu_count": 2,
    "gpu_devices": [
        {
            "name": "NVIDIA GeForce RTX 3080",
            "memory_total": 10737418240
        },
        {
            "name": "NVIDIA GeForce RTX 3080",
            "memory_total": 10737418240
        }
    ],
    "memory": {
        "total": 62.70906448364258
    }
}
